{
    "1416": {
        "sample_id": "1416",
        "ans_1": "Claudia_Mo",
        "ans_2": "Claudia_Mo"
    },
    "152": {
        "sample_id": "152",
        "ans_1": "Iron_Man",
        "ans_2": "Iron_Man"
    },
    "605": {
        "sample_id": "605",
        "ans_1": "Tian_Shan",
        "ans_2": "Tian_Shan"
    },
    "359": {
        "sample_id": "359",
        "ans_1": "Stockholm,_Sweden",
        "ans_2": "Stockholm"
    },
    "865": {
        "sample_id": "865",
        "ans_1": "Melastoma_malabathricum",
        "ans_2": "Melastoma_malabathricum"
    },
    "1355": {
        "sample_id": "1355",
        "ans_1": "Scottish_Aviation_Bulldog",
        "ans_2": "Scottish_Aviation_Bulldog"
    },
    "862": {
        "sample_id": "862",
        "ans_1": "Rick_Perry",
        "ans_2": "Rick_Perry"
    },
    "1132": {
        "sample_id": "1132",
        "ans_1": "Arkadiusz_Milik",
        "ans_2": "Arkadiusz_Milik"
    },
    "41": {
        "sample_id": "41",
        "ans_1": "China",
        "ans_2": "China"
    },
    "905": {
        "sample_id": "905",
        "ans_1": "Concordia_University_(Quebec)",
        "ans_2": "Concordia_University"
    }
}